Workbook

Sheet Assumptions
A1: FlowCue AI — Financial Model Assumptions
A2: Illustrative planning assumptions only — not committed figures. To be replaced with real funnel data as beta/launch metrics exist. See Business Plan §5-6.
A4: Growth & Conversion
A5: Month 1 new Free signups | B5: 500 | C5: Source: founder estimate, beta-scale starting point
A6: Monthly signup growth rate | B6: 0.08 | C6: Illustrative — validate against beta signup velocity
A7: Free → Pro conversion rate | B7: 0.045 | C7: Midpoint of 3-6% range cited in Business Plan §6
A8: Monthly Pro churn rate | B8: 0.04 | C8: Target <5% per Business Plan §6
A9: Life Events purchase rate (of new Free signups) | B9: 0.015 | C9: Illustrative — one-shot buyers, not a repeat-purchase segment
A11: Pricing
A12: Pro — monthly plan price | B12: 12.99
A13: Pro — annual plan price (effective monthly) | B13: 8.25 | C13: $99/yr ÷ 12
A14: Share of Pro subs on annual plan | B14: 0.3 | C14: Illustrative mix assumption
A15: Life Events one-time price | B15: 19.99
A17: B2B (Team / Education / Enterprise) — placeholder ramp
A18: Monthly B2B revenue at Month 7 (ramp start) | B18: 2000 | C18: Placeholder only — real figure depends on sales pipeline, not self-serve conversion (Business Plan §6)
A19: B2B monthly revenue growth rate (from Month 7) | B19: 0.12 | C19: Illustrative
A21: Unit Economics Check
A22: Blended CAC (illustrative, from Business Plan §5) | B22: 12

Sheet Summary
A1: FlowCue AI — Financial Model Summary
A2: Illustrative projection built on Assumptions tab — see notes there before citing any figure externally.
A4: Metric | B4: Year 1 (Mo. 1-12) | C4: Year 2 (Mo. 13-24)
A5: Total Revenue | B5: =SUM('Monthly Model'!K4:K15) -> 43369.041 | C5: =SUM('Monthly Model'!K16:K27) -> 202024.39
A6: — Pro subscription revenue | B6: =SUM('Monthly Model'!G4:G15) -> 24293.517 | C6: =SUM('Monthly Model'!G16:G27) -> 99590.778
A7: — Life Events revenue | B7: =SUM('Monthly Model'!I4:I15) -> 2845.1457 | C7: =SUM('Monthly Model'!I16:I27) -> 7164.5608
A8: — B2B revenue | B8: =SUM('Monthly Model'!J4:J15) -> 16230.378 | C8: =SUM('Monthly Model'!J16:J27) -> 95269.052
A9: Ending MRR (Pro + B2B) | B9: ='Monthly Model'!G15+'Monthly Model'!J15 -> 7657.6269 | C9: ='Monthly Model'!G27+'Monthly Model'!J27 -> 26671.831
A10: Ending ARR (annualized) | B10: =B9*12 -> 91891.523 | C10: =C9*12 -> 320061.98
A11: Ending Pro Subscribers | B11: ='Monthly Model'!E15 -> 357.27382 | C11: ='Monthly Model'!E27 -> 1118.5814
A12: Ending Cumulative Free Users | B12: ='Monthly Model'!C15 -> 9488.5632 | C12: ='Monthly Model'!C27 -> 33382.38
A14: Unit Economics
A15: Estimated Pro LTV (ARPU ÷ monthly churn) | B15: ='Monthly Model'!F4/Assumptions!$B$8 -> 289.2
A16: Blended CAC (from Assumptions) | B16: =Assumptions!$B$22 -> 12
A17: LTV : CAC ratio | B17: =B15/B16 -> 24.1
A19: Note: a healthy SaaS benchmark is LTV:CAC ≥ 3x. This is a planning heuristic, not a guarantee — real CAC and churn should replace the Assumptions-tab placeholders once beta/launch data exists.

Sheet Monthly Model
A1: FlowCue AI — 24-Month Model
A3: Month | B3: New Free Signups | C3: Cumulative Free Users | D3: New Pro Conversions | E3: Total Pro Subscribers | F3: Blended Pro ARPU | G3: Pro MRR | H3: Life Events Buyers | I3: Life Events Revenue | J3: B2B Revenue | K3: Total MRR + One-Time Revenue | L3: Cumulative Revenue
A4: 1 | B4: =Assumptions!$B$5 -> 500 | C4: =B4 -> 500 | D4: =B4*Assumptions!$B$7 -> 22.5 | E4: =D4 -> 22.5 | F4: =Assumptions!$B$12*(1-Assumptions!$B$14)+Assumptions!$B$13*Assumptions!$B$14 -> 11.568 | G4: =E4*F4 -> 260.28 | H4: =B4*Assumptions!$B$9 -> 7.5 | I4: =H4*Assumptions!$B$15 -> 149.925 | J4: =0 -> 0 | K4: =G4+I4+J4 -> 410.205 | L4: =K4 -> 410.205
A5: 2 | B5: =B4*(1+Assumptions!$B$6) -> 540 | C5: =C4+B5 -> 1040 | D5: =B5*Assumptions!$B$7 -> 24.3 | E5: =E4*(1-Assumptions!$B$8)+D5 -> 45.9 | F5: =Assumptions!$B$12*(1-Assumptions!$B$14)+Assumptions!$B$13*Assumptions!$B$14 -> 11.568 | G5: =E5*F5 -> 530.9712 | H5: =B5*Assumptions!$B$9 -> 8.1 | I5: =H5*Assumptions!$B$15 -> 161.919 | J5: =0 -> 0 | K5: =G5+I5+J5 -> 692.8902 | L5: =L4+K5 -> 1103.0952
A6: 3 | B6: =B5*(1+Assumptions!$B$6) -> 583.2 | C6: =C5+B6 -> 1623.2 | D6: =B6*Assumptions!$B$7 -> 26.244 | E6: =E5*(1-Assumptions!$B$8)+D6 -> 70.308 | F6: =Assumptions!$B$12*(1-Assumptions!$B$14)+Assumptions!$B$13*Assumptions!$B$14 -> 11.568 | G6: =E6*F6 -> 813.32294 | H6: =B6*Assumptions!$B$9 -> 8.748 | I6: =H6*Assumptions!$B$15 -> 174.87252 | J6: =0 -> 0 | K6: =G6+I6+J6 -> 988.19546 | L6: =L5+K6 -> 2091.2907
A7: 4 | B7: =B6*(1+Assumptions!$B$6) -> 629.856 | C7: =C6+B7 -> 2253.056 | D7: =B7*Assumptions!$B$7 -> 28.34352 | E7: =E6*(1-Assumptions!$B$8)+D7 -> 95.8392 | F7: =Assumptions!$B$12*(1-Assumptions!$B$14)+Assumptions!$B$13*Assumptions!$B$14 -> 11.568 | G7: =E7*F7 -> 1108.6679 | H7: =B7*Assumptions!$B$9 -> 9.44784 | I7: =H7*Assumptions!$B$15 -> 188.86232 | J7: =0 -> 0 | K7: =G7+I7+J7 -> 1297.5302 | L7: =L6+K7 -> 3388.8209
A8: 5 | B8: =B7*(1+Assumptions!$B$6) -> 680.24448 | C8: =C7+B8 -> 2933.3005 | D8: =B8*Assumptions!$B$7 -> 30.611002 | E8: =E7*(1-Assumptions!$B$8)+D8 -> 122.61663 | F8: =Assumptions!$B$12*(1-Assumptions!$B$14)+Assumptions!$B$13*Assumptions!$B$14 -> 11.568 | G8: =E8*F8 -> 1418.4292 | H8: =B8*Assumptions!$B$9 -> 10.203667 | I8: =H8*Assumptions!$B$15 -> 203.97131 | J8: =0 -> 0 | K8: =G8+I8+J8 -> 1622.4005 | L8: =L7+K8 -> 5011.2214
A9: 6 | B9: =B8*(1+Assumptions!$B$6) -> 734.66404 | C9: =C8+B9 -> 3667.9645 | D9: =B9*Assumptions!$B$7 -> 33.059882 | E9: =E8*(1-Assumptions!$B$8)+D9 -> 150.77185 | F9: =Assumptions!$B$12*(1-Assumptions!$B$14)+Assumptions!$B$13*Assumptions!$B$14 -> 11.568 | G9: =E9*F9 -> 1744.1288 | H9: =B9*Assumptions!$B$9 -> 11.019961 | I9: =H9*Assumptions!$B$15 -> 220.28901 | J9: =0 -> 0 | K9: =G9+I9+J9 -> 1964.4178 | L9: =L8+K9 -> 6975.6391
A10: 7 | B10: =B9*(1+Assumptions!$B$6) -> 793.43716 | C10: =C9+B10 -> 4461.4017 | D10: =B10*Assumptions!$B$7 -> 35.704672 | E10: =E9*(1-Assumptions!$B$8)+D10 -> 180.44565 | F10: =Assumptions!$B$12*(1-Assumptions!$B$14)+Assumptions!$B$13*Assumptions!$B$14 -> 11.568 | G10: =E10*F10 -> 2087.3953 | H10: =B10*Assumptions!$B$9 -> 11.901557 | I10: =H10*Assumptions!$B$15 -> 237.91213 | J10: =Assumptions!$B$18 -> 2000 | K10: =G10+I10+J10 -> 4325.3074 | L10: =L9+K10 -> 11300.947
A11: 8 | B11: =B10*(1+Assumptions!$B$6) -> 856.91213 | C11: =C10+B11 -> 5318.3138 | D11: =B11*Assumptions!$B$7 -> 38.561046 | E11: =E10*(1-Assumptions!$B$8)+D11 -> 211.78887 | F11: =Assumptions!$B$12*(1-Assumptions!$B$14)+Assumptions!$B$13*Assumptions!$B$14 -> 11.568 | G11: =E11*F11 -> 2449.9736 | H11: =B11*Assumptions!$B$9 -> 12.853682 | I11: =H11*Assumptions!$B$15 -> 256.9451 | J11: =J10*(1+Assumptions!$B$19) -> 2240 | K11: =G11+I11+J11 -> 4946.9187 | L11: =L10+K11 -> 16247.865
A12: 9 | B12: =B11*(1+Assumptions!$B$6) -> 925.46511 | C12: =C11+B12 -> 6243.7789 | D12: =B12*Assumptions!$B$7 -> 41.64593 | E12: =E11*(1-Assumptions!$B$8)+D12 -> 244.96324 | F12: =Assumptions!$B$12*(1-Assumptions!$B$14)+Assumptions!$B$13*Assumptions!$B$14 -> 11.568 | G12: =E12*F12 -> 2833.7348 | H12: =B12*Assumptions!$B$9 -> 13.881977 | I12: =H12*Assumptions!$B$15 -> 277.50071 | J12: =J11*(1+Assumptions!$B$19) -> 2508.8 | K12: =G12+I12+J12 -> 5620.0355 | L12: =L11+K12 -> 21867.901
A13: 10 | B13: =B12*(1+Assumptions!$B$6) -> 999.50231 | C13: =C12+B13 -> 7243.2812 | D13: =B13*Assumptions!$B$7 -> 44.977604 | E13: =E12*(1-Assumptions!$B$8)+D13 -> 280.14232 | F13: =Assumptions!$B$12*(1-Assumptions!$B$14)+Assumptions!$B$13*Assumptions!$B$14 -> 11.568 | G13: =E13*F13 -> 3240.6863 | H13: =B13*Assumptions!$B$9 -> 14.992535 | I13: =H13*Assumptions!$B$15 -> 299.70077 | J13: =J12*(1+Assumptions!$B$19) -> 2809.856 | K13: =G13+I13+J13 -> 6350.2431 | L13: =L12+K13 -> 28218.144
A14: 11 | B14: =B13*(1+Assumptions!$B$6) -> 1079.4625 | C14: =C13+B14 -> 8322.7437 | D14: =B14*Assumptions!$B$7 -> 48.575812 | E14: =E13*(1-Assumptions!$B$8)+D14 -> 317.51244 | F14: =Assumptions!$B$12*(1-Assumptions!$B$14)+Assumptions!$B$13*Assumptions!$B$14 -> 11.568 | G14: =E14*F14 -> 3672.9839 | H14: =B14*Assumptions!$B$9 -> 16.191937 | I14: =H14*Assumptions!$B$15 -> 323.67683 | J14: =J13*(1+Assumptions!$B$19) -> 3147.0387 | K14: =G14+I14+J14 -> 7143.6994 | L14: =L13+K14 -> 35361.843
A15: 12 | B15: =B14*(1+Assumptions!$B$6) -> 1165.8195 | C15: =C14+B15 -> 9488.5632 | D15: =B15*Assumptions!$B$7 -> 52.461877 | E15: =E14*(1-Assumptions!$B$8)+D15 -> 357.27382 | F15: =Assumptions!$B$12*(1-Assumptions!$B$14)+Assumptions!$B$13*Assumptions!$B$14 -> 11.568 | G15: =E15*F15 -> 4132.9435 | H15: =B15*Assumptions!$B$9 -> 17.487292 | I15: =H15*Assumptions!$B$15 -> 349.57098 | J15: =J14*(1+Assumptions!$B$19) -> 3524.6834 | K15: =G15+I15+J15 -> 8007.1979 | L15: =L14+K15 -> 43369.041
A16: 13 | B16: =B15*(1+Assumptions!$B$6) -> 1259.0851 | C16: =C15+B16 -> 10747.648 | D16: =B16*Assumptions!$B$7 -> 56.658828 | E16: =E15*(1-Assumptions!$B$8)+D16 -> 399.64169 | F16: =Assumptions!$B$12*(1-Assumptions!$B$14)+Assumptions!$B$13*Assumptions!$B$14 -> 11.568 | G16: =E16*F16 -> 4623.0551 | H16: =B16*Assumptions!$B$9 -> 18.886276 | I16: =H16*Assumptions!$B$15 -> 377.53665 | J16: =J15*(1+Assumptions!$B$19) -> 3947.6454 | K16: =G16+I16+J16 -> 8948.2371 | L16: =L15+K16 -> 52317.278
A17: 14 | B17: =B16*(1+Assumptions!$B$6) -> 1359.8119 | C17: =C16+B17 -> 12107.46 | D17: =B17*Assumptions!$B$7 -> 61.191534 | E17: =E16*(1-Assumptions!$B$8)+D17 -> 444.84756 | F17: =Assumptions!$B$12*(1-Assumptions!$B$14)+Assumptions!$B$13*Assumptions!$B$14 -> 11.568 | G17: =E17*F17 -> 5145.9966 | H17: =B17*Assumptions!$B$9 -> 20.397178 | I17: =H17*Assumptions!$B$15 -> 407.73959 | J17: =J16*(1+Assumptions!$B$19) -> 4421.3628 | K17: =G17+I17+J17 -> 9975.099 | L17: =L16+K17 -> 62292.377
A18: 15 | B18: =B17*(1+Assumptions!$B$6) -> 1468.5968 | C18: =C17+B18 -> 13576.057 | D18: =B18*Assumptions!$B$7 -> 66.086857 | E18: =E17*(1-Assumptions!$B$8)+D18 -> 493.14051 | F18: =Assumptions!$B$12*(1-Assumptions!$B$14)+Assumptions!$B$13*Assumptions!$B$14 -> 11.568 | G18: =E18*F18 -> 5704.6495 | H18: =B18*Assumptions!$B$9 -> 22.028952 | I18: =H18*Assumptions!$B$15 -> 440.35875 | J18: =J17*(1+Assumptions!$B$19) -> 4951.9264 | K18: =G18+I18+J18 -> 11096.935 | L18: =L17+K18 -> 73389.312
A19: 16 | B19: =B18*(1+Assumptions!$B$6) -> 1586.0846 | C19: =C18+B19 -> 15162.142 | D19: =B19*Assumptions!$B$7 -> 71.373805 | E19: =E18*(1-Assumptions!$B$8)+D19 -> 544.7887 | F19: =Assumptions!$B$12*(1-Assumptions!$B$14)+Assumptions!$B$13*Assumptions!$B$14 -> 11.568 | G19: =E19*F19 -> 6302.1156 | H19: =B19*Assumptions!$B$9 -> 23.791268 | I19: =H19*Assumptions!$B$15 -> 475.58745 | J19: =J18*(1+Assumptions!$B$19) -> 5546.1575 | K19: =G19+I19+J19 -> 12323.861 | L19: =L18+K19 -> 85713.172
A20: 17 | B20: =B19*(1+Assumptions!$B$6) -> 1712.9713 | C20: =C19+B20 -> 16875.113 | D20: =B20*Assumptions!$B$7 -> 77.083709 | E20: =E19*(1-Assumptions!$B$8)+D20 -> 600.08086 | F20: =Assumptions!$B$12*(1-Assumptions!$B$14)+Assumptions!$B$13*Assumptions!$B$14 -> 11.568 | G20: =E20*F20 -> 6941.7354 | H20: =B20*Assumptions!$B$9 -> 25.69457 | I20: =H20*Assumptions!$B$15 -> 513.63445 | J20: =J19*(1+Assumptions!$B$19) -> 6211.6964 | K20: =G20+I20+J20 -> 13667.066 | L20: =L19+K20 -> 99380.239
A21: 18 | B21: =B20*(1+Assumptions!$B$6) -> 1850.009 | C21: =C20+B21 -> 18725.122 | D21: =B21*Assumptions!$B$7 -> 83.250406 | E21: =E20*(1-Assumptions!$B$8)+D21 -> 659.32803 | F21: =Assumptions!$B$12*(1-Assumptions!$B$14)+Assumptions!$B$13*Assumptions!$B$14 -> 11.568 | G21: =E21*F21 -> 7627.1067 | H21: =B21*Assumptions!$B$9 -> 27.750135 | I21: =H21*Assumptions!$B$15 -> 554.72521 | J21: =J20*(1+Assumptions!$B$19) -> 6957.1 | K21: =G21+I21+J21 -> 15138.932 | L21: =L20+K21 -> 114519.17
A22: 19 | B22: =B21*(1+Assumptions!$B$6) -> 1998.0097 | C22: =C21+B22 -> 20723.132 | D22: =B22*Assumptions!$B$7 -> 89.910439 | E22: =E21*(1-Assumptions!$B$8)+D22 -> 722.86535 | F22: =Assumptions!$B$12*(1-Assumptions!$B$14)+Assumptions!$B$13*Assumptions!$B$14 -> 11.568 | G22: =E22*F22 -> 8362.1063 | H22: =B22*Assumptions!$B$9 -> 29.970146 | I22: =H22*Assumptions!$B$15 -> 599.10322 | J22: =J21*(1+Assumptions!$B$19) -> 7791.952 | K22: =G22+I22+J22 -> 16753.162 | L22: =L21+K22 -> 131272.33
... A27: 24 | B27: =B26*(1+Assumptions!$B$6) -> 2935.7318 | C27: =C26+B27 -> 33382.38 | D27: =B27*Assumptions!$B$7 -> 132.10793 | E27: =E26*(1-Assumptions!$B$8)+D27 -> 1118.5814 | F27: =Assumptions!$B$12*(1-Assumptions!$B$14)+Assumptions!$B$13*Assumptions!$B$14 -> 11.568 | G27: =E27*F27 -> 12939.75 | H27: =B27*Assumptions!$B$9 -> 44.035977 | I27: =H27*Assumptions!$B$15 -> 880.27919 | J27: =J26*(1+Assumptions!$B$19) -> 13732.082 | K27: =G27+I27+J27 -> 27552.111 | L27: =L26+K27 -> 245393.43
